signal_analog/__init__.py
signal_analog/charts.py
signal_analog/cli.py
signal_analog/combinators.py
signal_analog/dashboards.py
signal_analog/detectors.py
signal_analog/errors.py
signal_analog/eventoverlays.py
signal_analog/filters.py
signal_analog/flow.py
signal_analog/logging.yaml
signal_analog/resources.py
signal_analog/util.py
signal_analog/error/__init__.py
signal_analog/error/signalfx.py
signal_analog-2.10.1.dist-info/LICENSE
signal_analog-2.10.1.dist-info/METADATA
signal_analog-2.10.1.dist-info/WHEEL
signal_analog-2.10.1.dist-info/top_level.txt
signal_analog-2.10.1.dist-info/RECORD
