Metadata-Version: 2.1
Name: signal-analog
Version: 2.10.1
Summary: A troposphere-like library for managing SignalFxCharts, Dashboards, and Detectors.
Home-page: https://github.com/Nike-inc/signal_analog
Author: Fernando Freire
Author-email: fernando.freire@nike.com
License: BSD 3-Clause License
Keywords: signal_analog signalfx dashboards charts detectors monitoring signalflow
Classifier: Programming Language :: Python :: 2
Classifier: Development Status :: 5 - Production/Stable
Classifier: Environment :: Console
Classifier: Intended Audience :: Developers
Classifier: License :: OSI Approved :: BSD License
Classifier: Natural Language :: English
Classifier: Operating System :: OS Independent
Classifier: Programming Language :: Python :: 3
Classifier: Topic :: Software Development :: Libraries :: Python Modules
Classifier: Topic :: Software Development :: Libraries
Classifier: Topic :: Utilities
License-File: LICENSE
Requires-Dist: enum34
Requires-Dist: six
Requires-Dist: requests
Requires-Dist: click
Requires-Dist: email-validator
Requires-Dist: pyyaml
Requires-Dist: markdown
Requires-Dist: deprecation
